{"plan":{"cityCenter":[116.402,39.907],"days":[{"summary":"第一天：故宫与天安门广场探索，预算落点在住宿与餐饮上","routes":[],"pois":[{"name":"北京饭店","coord":[],"type":"hotel"},{"name":"天安门广场","coord":[],"type":"sight"},{"name":"人民英雄纪念碑","coord":[],"type":"sight"},{"name":"全聚德（前门店）","coord":[],"type":"restaurant"},{"name":"故宫博物院","coord":[],"type":"sight"},{"name":"京味斋餐厅","coord":[],"type":"restaurant"}]},{"summary":"第二天：长城与颐和园之旅，预算落点在交通与门票上","routes":[],"pois":[{"name":"八达岭长城","coord":[],"type":"sight"},{"name":"长城脚下的农家菜馆","coord":[],"type":"restaurant"},{"name":"颐和园","coord":[],"type":"sight"},{"name":"北京华尔道夫酒店","coord":[],"type":"hotel"},{"name":"老北京炸酱面馆","coord":[],"type":"restaurant"},{"name":"中国国家博物馆","coord":[],"type":"museum"}]},{"summary":"第三天：奥林匹克公园与返程准备，预算落点在交通与餐饮上","routes":[{"polyline":"116.362244,39.920564;116.459053,39.906297;116.451517,40.020195","color":"#3b82f6"}],"pois":[{"name":"北京奥林匹克公园","coord":[],"type":"sight"},{"name":"鸟巢","coord":[116.362244,39.920564],"type":"sight"},{"name":"水立方","coord":[116.459053,39.906297],"type":"sight"},{"name":"中国国家博物馆","coord":[],"type":"museum"},{"name":"涮羊肉餐厅","coord":[],"type":"restaurant"},{"name":"首都国际机场","coord":[116.451517,40.020195],"type":"sight"}]}],"baseBudget":{"amount":470,"currency":"CNY"}},"rawText":"北京三日游行程规划\n\n第一天：故宫与天安门广场探索  \n上午，我们从北京首都国际机场出发，乘坐出租车前往位于东城区的北京饭店，入住后稍作休息。随后步行至天安门广场，感受庄严的升旗仪式，并参观人民英雄纪念碑。中午在附近的全聚德（前门店）享用午餐，品尝经典的烤鸭。下午前往故宫博物院，游览紫禁城的宏伟建筑群，体验明清两代皇家宫殿的辉煌历史。傍晚返回酒店休息，晚餐选择在酒店内的京味斋餐厅，品尝地道的京味菜肴。\n\n第二天：长城与颐和园之旅  \n清晨，搭乘地铁13号线前往八达岭长城，游览世界七大奇迹之一的长城，欣赏壮丽的自然风光。中午在长城脚下的农家菜馆用餐，体验当地特色美食。下午前往颐和园，漫步昆明湖畔，参观万寿山、长廊等著名景点，感受皇家园林的精致与优雅。晚上返回市区，入住北京华尔道夫酒店，晚餐选择在附近的老北京炸酱面馆，品尝传统面食。\n\n第三天：奥林匹克公园与返程准备  \n上午前往北京奥林匹克公园，参观鸟巢和水立方，感受现代体育场馆的魅力。随后步行至中国国家博物馆，了解中国的历史文化。中午在公园附近的涮羊肉餐厅享用午餐，体验北京特色饮食。下午前往首都国际机场，办理登机手续，结束愉快的北京三日游。\n\n### 预算  \n- 住宿：北京饭店（2晚）：约 800 CNY/晚 × 2 晚 ≈ 1600 CNY  \n- 交通：市区打车（机场↔饭店）：约 50 CNY/次 × 2 次 ≈ 100 CNY  \n- 餐饮：全聚德（前门店）：约 200 CNY/顿 × 1 顿 ≈ 200 CNY  \n- 门票：故宫博物院门票：约 60 CNY/张 × 1 张 ≈ 60 CNY  \n- 交通：地铁13号线（八达岭）：约 40 CNY/次 × 2 次 ≈ 80 CNY  \n- 餐饮：长城脚下的农家菜馆：约 150 CNY/顿 × 1 顿 ≈ 150 CNY  \n- 门票：颐和园门票：约 50 CNY/张 × 1 张 ≈ 50 CNY  \n- 餐饮：涮羊肉餐厅：约 120 CNY/顿 × 1 顿 ≈ 120 CNY  \n- 交通：地铁13号线（奥森公园）：约 30 CNY/次 × 2 次 ≈ 60 CNY  \n- 餐饮：老北京炸酱面馆：约 80 CNY/顿 × 1 顿 ≈ 80 CNY  \n- 门票：中国国家博物馆门票：约 30 CNY/张 × 1 张 ≈ 30 CNY  \n\n类别小计：住宿 1600 CNY，交通 240 CNY，餐饮 550 CNY，门票 140 CNY  \n总花费（估算）：2530 CNY  \n预算余量（估算）：470 CNY\n合计：0 CNY","budget":{"currency":"CNY","categories":[{"name":"住宿","items":[{"name":"北京饭店（2晚）：约 800 CNY/晚 × 2 晚","amount":1600,"currency":"CNY"}],"total":1600,"currency":"CNY"},{"name":"交通","items":[{"name":"市区打车（机场↔饭店）：约 50 CNY/次 × 2 次","amount":100,"currency":"CNY"},{"name":"地铁13号线（八达岭）：约 40 CNY/次 × 2 次","amount":80,"currency":"CNY"},{"name":"地铁13号线（奥森公园）：约 30 CNY/次 × 2 次","amount":60,"currency":"CNY"}],"total":240,"currency":"CNY"},{"name":"餐饮","items":[{"name":"全聚德（前门店）：约 200 CNY/顿 × 1 顿","amount":200,"currency":"CNY"},{"name":"长城脚下的农家菜馆：约 150 CNY/顿 × 1 顿","amount":150,"currency":"CNY"},{"name":"涮羊肉餐厅：约 120 CNY/顿 × 1 顿","amount":120,"currency":"CNY"},{"name":"老北京炸酱面馆：约 80 CNY/顿 × 1 顿","amount":80,"currency":"CNY"}],"total":550,"currency":"CNY"},{"name":"门票","items":[{"name":"故宫博物院门票：约 60 CNY/张 × 1 张","amount":60,"currency":"CNY"},{"name":"颐和园门票：约 50 CNY/张 × 1 张","amount":50,"currency":"CNY"},{"name":"中国国家博物馆门票：约 30 CNY/张 × 1 张","amount":30,"currency":"CNY"}],"total":140,"currency":"CNY"},{"name":"类别","items":[],"total":140,"currency":"CNY"}],"grandTotal":2670,"aligned":true},"budgetAligned":true,"daily":[{"title":"第 1 天","attractions":["天安门广场","人民英雄纪念碑","故宫博物院"],"lodging":["北京饭店"],"restaurants":["全聚德（前门店）","京味斋餐厅"],"transport":[]},{"title":"第 2 天","attractions":["八达岭长城","颐和园","中国国家博物馆"],"lodging":["北京华尔道夫酒店"],"restaurants":["长城脚下的农家菜馆","老北京炸酱面馆"],"transport":[]},{"title":"第 3 天","attractions":["北京奥林匹克公园","鸟巢","水立方","中国国家博物馆","首都国际机场"],"lodging":[],"restaurants":["涮羊肉餐厅"],"transport":[]}]}